pydantic_typer/__about__.py
pydantic_typer/__init__.py
pydantic_typer/main.py
pydantic_typer/utils.py
pydantic_typer-0.0.13.dist-info/METADATA
pydantic_typer-0.0.13.dist-info/WHEEL
pydantic_typer-0.0.13.dist-info/licenses/LICENSE.txt
pydantic_typer-0.0.13.dist-info/RECORD
