Metadata-Version: 2.3
Name: pydantic-typer
Version: 0.0.13
Summary: Typer extension to enable pydantic support
Project-URL: Documentation, https://github.com/pypae/pydantic-typer#readme
Project-URL: Issues, https://github.com/pypae/pydantic-typer/issues
Project-URL: Source, https://github.com/pypae/pydantic-typer
Author-email: Patrick Düggelin <patrick.dueggelin@live.de>
License: MIT
Classifier: Development Status :: 4 - Beta
Classifier: Programming Language :: Python
Classifier: Programming Language :: Python :: 3.8
Classifier: Programming Language :: Python :: 3.9
Classifier: Programming Language :: Python :: 3.10
Classifier: Programming Language :: Python :: 3.11
Classifier: Programming Language :: Python :: 3.12
Classifier: Programming Language :: Python :: Implementation :: CPython
Classifier: Programming Language :: Python :: Implementation :: PyPy
Requires-Python: >=3.8
Requires-Dist: pydantic
Requires-Dist: typer
